{
    "SheetMusic": [
        {
            "key": "timeSignature",
            "label": "拍號",
            "type": "SingleChoice",
            "options": [
                {
                    "label": "2/4",
                    "value": "2/4"
                },
                {
                    "label": "3/4",
                    "value": "3/4"
                },
                {
                    "label": "4/4",
                    "value": "4/4"
                },
                {
                    "label": "2/2",
                    "value": "2/2"
                },
                {
                    "label": "3/8",
                    "value": "3/8"
                },
                {
                    "label": "6/8",
                    "value": "6/8"
                },
                {
                    "label": "9/8",
                    "value": "9/8"
                },
                {
                    "label": "12/8",
                    "value": "12/8"
                },
                {
                    "label": "5/4",
                    "value": "5/4"
                },
                {
                    "label": "7/4",
                    "value": "7/4"
                },
                {
                    "label": "5/8",
                    "value": "5/8"
                },
                {
                    "label": "7/8",
                    "value": "7/8"
                },
                {
                    "label": "11/8",
                    "value": "11/8"
                }
            ],
            "initialValue": 2
        },
        {
            "key": "speed",
            "type": "IntInputBox",
            "label": "速度",
            "initialValue": 80,
            "min": 40,
            "max": 400
        },
        {
            "hide": true,
            "key": "rowsSM",
            "type": "IntInputBox",
            "label": "行數",
            "initialValue": 1,
            "min": 1,
            "max": 20
        },
        {
            "key": "lengthSM",
            "type": "IntInputBox",
            "label": "長度",
            "initialValue": 8,
            "min": 1,
            "max": 32
        },
        {
            "key": "scale",
            "type": "IntInputBox",
            "label": "大小",
            "initialValue": 25,
            "min": 1,
            "max": 50
        },
        {
            "key": "rightHand",
            "label": "右手",
            "type": "SingleChoice",
            "options": [
                {
                    "label": "No",
                    "value": "No"
                },
                {
                    "label": "ST",
                    "value": "ST"
                },
                {
                    "label": "Ch",
                    "value": "Ch"
                }
            ],
            "initialValue": 1
        },
        {
            "key": "leftHand",
            "type": "SingleChoice",
            "label": "左手",
            "options": [
                {
                    "label": "No",
                    "value": "No"
                },
                {
                    "label": "ST",
                    "value": "ST"
                },
                {
                    "label": "Sa",
                    "value": "Sa"
                },
                {
                    "label": "Ch",
                    "value": "Ch"
                }
            ],
            "initialValue": 2
        }
    ],
    "SightReadin": [
        {
            "key": "reference",
            "type": "MultipleChoice",
            "label": "參考點",
            "options": [
                {
                    "label": "C",
                    "value": "C"
                },
                {
                    "label": "♯C",
                    "value": "^C"
                },
                {
                    "label": "D",
                    "value": "D"
                },
                {
                    "label": "♯D",
                    "value": "^D"
                },
                {
                    "label": "E",
                    "value": "E"
                },
                {
                    "label": "F",
                    "value": "F"
                },
                {
                    "label": "♯F",
                    "value": "^F"
                },
                {
                    "label": "G",
                    "value": "G"
                },
                {
                    "label": "♯G",
                    "value": "^G"
                },
                {
                    "label": "A",
                    "value": "A"
                },
                {
                    "label": "♯A",
                    "value": "^A"
                },
                {
                    "label": "B",
                    "value": "B"
                }
            ],
            "initialValue": [
                0,
                7
            ]
        },
        {
            "key": "interval",
            "type": "MultipleChoice",
            "label": "音程",
            "options": [
                {
                    "label": 1,
                    "value": 0
                },
                {
                    "label": 2,
                    "value": 1
                },
                {
                    "label": 3,
                    "value": 2
                },
                {
                    "label": 4,
                    "value": 3
                },
                {
                    "label": 5,
                    "value": 4
                },
                {
                    "label": 6,
                    "value": 5
                },
                {
                    "label": 7,
                    "value": 6
                },
                {
                    "label": 8,
                    "value": 7
                },
                {
                    "label": 9,
                    "value": 8
                },
                {
                    "label": 10,
                    "value": 9
                }
            ]
        },
        {
            "key": "intervalDT",
            "type": "MultipleChoice",
            "label": "雙音音程",
            "options": [
                {
                    "label": 1,
                    "value": 0
                },
                {
                    "label": 2,
                    "value": 1
                },
                {
                    "label": 3,
                    "value": 2
                },
                {
                    "label": 4,
                    "value": 3
                },
                {
                    "label": 5,
                    "value": 4
                },
                {
                    "label": 6,
                    "value": 5
                },
                {
                    "label": 7,
                    "value": 6
                },
                {
                    "label": 8,
                    "value": 7
                },
                {
                    "label": 9,
                    "value": 8
                },
                {
                    "label": 10,
                    "value": 9
                }
            ],
            "initialValue": [
                0
            ]
        },
        {
            "hide": true,
            "key": "rannge",
            "type": "MultipleChoice",
            "label": "音域",
            "options": [
                {
                    "label": "C1",
                    "value": "C,,,"
                },
                {
                    "label": "G1",
                    "value": "G,,,"
                },
                {
                    "label": "C2",
                    "value": "C,,"
                },
                {
                    "label": "G2",
                    "value": "G,,"
                },
                {
                    "label": "C3",
                    "value": "C,"
                },
                {
                    "label": "G3",
                    "value": "G,"
                },
                {
                    "label": "C4",
                    "value": "C"
                },
                {
                    "label": "G4",
                    "value": "G"
                },
                {
                    "label": "C5",
                    "value": "C'"
                },
                {
                    "label": "G5",
                    "value": "G'"
                },
                {
                    "label": "C6",
                    "value": "C''"
                },
                {
                    "label": "G6",
                    "value": "G''"
                }
            ],
            "initialValue": [
                4,
                5,
                6,
                7,
                8,
                9
            ]
        },
        {
            "key": "tonality",
            "type": "SingleChoice",
            "label": "調性",
            "options": [
                {
                    "label": "C",
                    "value": "C"
                },
                {
                    "label": "G",
                    "value": "G"
                },
                {
                    "label": "D",
                    "value": "D"
                },
                {
                    "label": "A",
                    "value": "A"
                },
                {
                    "label": "E",
                    "value": "E"
                },
                {
                    "label": "B",
                    "value": "B"
                },
                {
                    "label": "F♯",
                    "value": "F#"
                },
                {
                    "label": "C♯",
                    "value": "C#"
                },
                {
                    "label": "F",
                    "value": "F"
                },
                {
                    "label": "B♭",
                    "value": "Bb"
                },
                {
                    "label": "E♭",
                    "value": "Eb"
                },
                {
                    "label": "A♭",
                    "value": "Ab"
                },
                {
                    "label": "D♭",
                    "value": "Db"
                },
                {
                    "label": "G♭",
                    "value": "Gb"
                },
                {
                    "label": "C♭",
                    "value": "Cb"
                }
            ],
            "initialValue": 0
        }
    ]
}